LICENSE
rbo/__init__.py
rbo/rbo.py
rbo-0.1.3.dist-info/LICENSE
rbo-0.1.3.dist-info/WHEEL
rbo-0.1.3.dist-info/METADATA
rbo-0.1.3.dist-info/RECORD
