Metadata-Version: 2.1
Name: rbo
Version: 0.1.3
Summary: Simple library to calculate Rank-biased Overlap between two lists
Home-page: https://github.com/changyaochen/rbo
License: MIT
Keywords: rbo
Author: Changyao Chen
Author-email: changyao.chen@gmail.com
Requires-Python: >=3.7,<4.0
Classifier: License :: OSI Approved :: MIT License
Classifier: Programming Language :: Python :: 3
Classifier: Programming Language :: Python :: 3.7
Classifier: Programming Language :: Python :: 3.8
Classifier: Programming Language :: Python :: 3.9
Classifier: Programming Language :: Python :: 3.10
Classifier: Programming Language :: Python :: 3.11
Requires-Dist: numpy (>=1.18,<2.0)
Requires-Dist: tqdm (>=4.59.0,<5.0.0)
Project-URL: Repository, https://github.com/changyaochen/rbo
